setup.py
cbipy/__init__.py
cbipy.egg-info/PKG-INFO
cbipy.egg-info/SOURCES.txt
cbipy.egg-info/dependency_links.txt
cbipy.egg-info/not-zip-safe
cbipy.egg-info/top_level.txt