Metadata-Version: 1.0
Name: cbipy
Version: 0.1
Summary: My little application
Home-page: http://github.com/kip-marks/cbipy
Author: Kip Marks
Author-email: kip.marks@gmail.com
License: MIT
Platform: UNKNOWN
